contextmenu/__init__.py
contextmenu/admin.py
contextmenu/apps.py
contextmenu/models.py
contextmenu/options.py
contextmenu/tests.py
contextmenu/views.py
contextmenu/templates/contextmenu/base.html
contextmenu/templates/contextmenu/dropdown.html
django_admin_contextmenu-0.1.0.dist-info/METADATA
django_admin_contextmenu-0.1.0.dist-info/WHEEL
django_admin_contextmenu-0.1.0.dist-info/top_level.txt
django_admin_contextmenu-0.1.0.dist-info/RECORD
